granica/__init__.py
granica/bolt_router.py
granica_sdk-2.2.0.dist-info/LICENSE
granica_sdk-2.2.0.dist-info/METADATA
granica_sdk-2.2.0.dist-info/WHEEL
granica_sdk-2.2.0.dist-info/top_level.txt
granica_sdk-2.2.0.dist-info/RECORD
