Metadata-Version: 2.1
Name: granica-sdk
Version: 2.2.0
Summary: Granica Python SDK
Home-page: https://github.com/project-n-oss/projectn-bolt-python
Author: Project N
Classifier: Programming Language :: Python :: 3
Classifier: Operating System :: OS Independent
Classifier: License :: OSI Approved :: Apache Software License
Classifier: Topic :: Software Development :: Libraries
Requires-Python: >=3
License-File: LICENSE
Requires-Dist: boto3
Requires-Dist: botocore
